LICENSE
MANIFEST.in
README.md
setup.py
bibcat_publisher.egg-info/PKG-INFO
bibcat_publisher.egg-info/SOURCES.txt
bibcat_publisher.egg-info/dependency_links.txt
bibcat_publisher.egg-info/requires.txt
bibcat_publisher.egg-info/top_level.txt
catalog/__init__.py
catalog/api.py
catalog/app.py
catalog/forms.py
catalog/views.py
catalog/static/css/bootstrap.min.css
catalog/static/css/fa-svg-with-js.css
catalog/static/js/bootstrap.bundle.min.js
catalog/static/js/fontawesome-all.js
catalog/static/js/jquery.min.js
catalog/static/js/popper.min.js
catalog/static/js/typeahead.bundle.min.js
catalog/templates/500.html
catalog/templates/base.html
catalog/templates/detail.html
catalog/templates/facets.html
catalog/templates/footer.html
catalog/templates/header.html
catalog/templates/index.html
catalog/templates/login.html
catalog/templates/navbar.html
catalog/templates/search-results.html
catalog/templates/search.html